nbnhhsh/__init__.py
nbnhhsh/cmd.py
nbnhhsh/nbnhhsh.py
nbnhhsh-1.1.1.dist-info/LICENSE
nbnhhsh-1.1.1.dist-info/METADATA
nbnhhsh-1.1.1.dist-info/WHEEL
nbnhhsh-1.1.1.dist-info/entry_points.txt
nbnhhsh-1.1.1.dist-info/top_level.txt
nbnhhsh-1.1.1.dist-info/RECORD
